flake8_num_positionl_args/__init__.py
flake8_num_positionl_args/num_positional_args_checker.py
flake8_num_positionl_args-0.0.2.dist-info/entry_points.txt
flake8_num_positionl_args-0.0.2.dist-info/WHEEL
flake8_num_positionl_args-0.0.2.dist-info/METADATA
flake8_num_positionl_args-0.0.2.dist-info/RECORD
